[
    {
        "key": "dbln",
        "value": "%7B%2261558640691524%22%3A%223Sjozbg1%22%2C%2261559581313136%22%3A%22fY64cory%22%7D",
        "domain": "facebook.com",
        "path": "/login/device-based/",
        "hostOnly": false,
        "creation": "2024-05-11T15:20:26.052Z",
        "lastAccessed": "2024-05-11T15:20:26.053Z"
    },
    {
        "key": "sb",
        "value": "YYs_ZoeljbvoKCJSwc78_YzM",
        "domain": "facebook.com",
        "path": "/",
        "hostOnly": false,
        "creation": "2024-05-11T15:20:26.053Z",
        "lastAccessed": "2024-05-11T15:20:26.053Z"
    },
    {
        "key": "wd",
        "value": "1920x953",
        "domain": "facebook.com",
        "path": "/",
        "hostOnly": false,
        "creation": "2024-05-11T15:20:26.053Z",
        "lastAccessed": "2024-05-11T15:20:26.053Z"
    },
    {
        "key": "datr",
        "value": "dIw_ZjROHJxWiFnlkIdu0IEJ",
        "domain": "facebook.com",
        "path": "/",
        "hostOnly": false,
        "creation": "2024-05-11T15:20:26.053Z",
        "lastAccessed": "2024-05-11T15:20:26.053Z"
    },
    {
        "key": "c_user",
        "value": "61559189954445",
        "domain": "facebook.com",
        "path": "/",
        "hostOnly": false,
        "creation": "2024-05-11T15:20:26.053Z",
        "lastAccessed": "2024-05-11T15:20:26.053Z"
    },
    {
        "key": "xs",
        "value": "27%3Aj2rbpOUYeXSPoA%3A2%3A1715440799%3A-1%3A-1",
        "domain": "facebook.com",
        "path": "/",
        "hostOnly": false,
        "creation": "2024-05-11T15:20:26.053Z",
        "lastAccessed": "2024-05-11T15:20:26.053Z"
    },
    {
        "key": "fr",
        "value": "0fJQ8esROHpxXJqHn.AWXbmxPzlZoalw-B4hN9Q4tEjqA.BmP4x0..AAA.0.0.BmP4yf.AWWZ8qV7qK0",
        "domain": "facebook.com",
        "path": "/",
        "hostOnly": false,
        "creation": "2024-05-11T15:20:26.053Z",
        "lastAccessed": "2024-05-11T15:20:26.053Z"
    },
    {
        "key": "presence",
        "value": "C%7B%22t3%22%3A%5B%5D%2C%22utc3%22%3A1715440814449%2C%22v%22%3A1%7D",
        "domain": "facebook.com",
        "path": "/",
        "hostOnly": false,
        "creation": "2024-05-11T15:20:26.053Z",
        "lastAccessed": "2024-05-11T15:20:26.053Z"
    }
]